pyworkers/__init__.py
pyworkers/_dist_info.py
pyworkers/persistent.py
pyworkers/persistent_process.py
pyworkers/persistent_remote.py
pyworkers/persistent_thread.py
pyworkers/pool.py
pyworkers/process.py
pyworkers/remote.py
pyworkers/remote_context.py
pyworkers/remote_pickle.py
pyworkers/remote_server.py
pyworkers/spawn_ssh_servers.py
pyworkers/thread.py
pyworkers/utils.py
pyworkers/version.py
pyworkers/worker.py
pyworkers/_remote_pickle/__init__.py
pyworkers/_remote_pickle/remote_pickler_3_6.py
pyworkers/_remote_pickle/state.py
pyworkers-1.0.3.post2.data/data/LICENSE
pyworkers-1.0.3.post2.data/data/README.md
pyworkers-1.0.3.post2.dist-info/LICENSE
pyworkers-1.0.3.post2.dist-info/METADATA
pyworkers-1.0.3.post2.dist-info/WHEEL
pyworkers-1.0.3.post2.dist-info/top_level.txt
pyworkers-1.0.3.post2.dist-info/RECORD
