Metadata-Version: 2.1
Name: pyworkers
Version: 1.0.3.post2
Summary: Library providing abstraction over different types of parallel jobs: threads, processes and remote processes.
Home-page: https://github.com/SamsungLabs/pyworkers
Download-URL: https://github.com/SamsungLabs/pyworkers
Author: Łukasz Dudziak
Author-email: l.dudziak@samsung.com
Requires-Python: >=3.6.0
License-File: LICENSE
